<?xml version="1.0" ?>
<SmellBaseline>
  <ManuallySuppressedIssues></ManuallySuppressedIssues>
  <CurrentIssues>
    <ID>MagicNumber:TipsyActivity.kt$TipsyActivity$100</ID>
    <ID>MaxLineLength:CalculateActivity.kt$CalculateActivity$private fun isYearlyInterestRateValid(yearlyInterestRate: Double?)</ID>
    <ID>MaximumLineLength:se.linerotech.module201.project4.CalculateActivity.kt:67</ID>
    <ID>NoWildcardImports:se.linerotech.module201.guide.ExampleInstrumentedTest.kt:5</ID>
    <ID>NoWildcardImports:se.linerotech.module201.guide.ExampleUnitTest.kt:3</ID>
    <ID>NoWildcardImports:se.linerotech.module201.project1.ExampleInstrumentedTest.kt:5</ID>
    <ID>NoWildcardImports:se.linerotech.module201.project1.ExampleUnitTest.kt:3</ID>
    <ID>NoWildcardImports:se.linerotech.module201.project2.ExampleInstrumentedTest.kt:5</ID>
    <ID>NoWildcardImports:se.linerotech.module201.project2.ExampleUnitTest.kt:3</ID>
    <ID>NoWildcardImports:se.linerotech.module201.project3.ExampleInstrumentedTest.kt:5</ID>
    <ID>NoWildcardImports:se.linerotech.module201.project3.ExampleUnitTest.kt:3</ID>
    <ID>NoWildcardImports:se.linerotech.module201.project4.ExampleInstrumentedTest.kt:5</ID>
    <ID>NoWildcardImports:se.linerotech.module201.project4.ExampleUnitTest.kt:3</ID>
    <ID>NoWildcardImports:se.linerotech.module201.project5.ExampleInstrumentedTest.kt:5</ID>
    <ID>NoWildcardImports:se.linerotech.module201.project5.ExampleUnitTest.kt:3</ID>
    <ID>NoWildcardImports:se.linerotech.module201.project6.ExampleInstrumentedTest.kt:5</ID>
    <ID>NoWildcardImports:se.linerotech.module201.project6.ExampleUnitTest.kt:3</ID>
    <ID>NoWildcardImports:se.linerotech.module202.guide.ExampleInstrumentedTest.kt:5</ID>
    <ID>NoWildcardImports:se.linerotech.module202.guide.ExampleUnitTest.kt:3</ID>
    <ID>NoWildcardImports:se.linerotech.module202.project1.ExampleInstrumentedTest.kt:5</ID>
    <ID>NoWildcardImports:se.linerotech.module202.project1.ExampleUnitTest.kt:3</ID>
    <ID>NoWildcardImports:se.linerotech.module202.project2.ExampleInstrumentedTest.kt:5</ID>
    <ID>NoWildcardImports:se.linerotech.module202.project2.ExampleUnitTest.kt:3</ID>
    <ID>NoWildcardImports:se.linerotech.module202.project3.ExampleInstrumentedTest.kt:5</ID>
    <ID>NoWildcardImports:se.linerotech.module202.project3.ExampleUnitTest.kt:3</ID>
    <ID>NoWildcardImports:se.linerotech.module202.project4.ExampleInstrumentedTest.kt:5</ID>
    <ID>NoWildcardImports:se.linerotech.module202.project4.ExampleUnitTest.kt:3</ID>
    <ID>NoWildcardImports:se.linerotech.module202.project5.ExampleInstrumentedTest.kt:5</ID>
    <ID>NoWildcardImports:se.linerotech.module202.project5.ExampleUnitTest.kt:3</ID>
    <ID>NoWildcardImports:se.linerotech.module202.project6.ExampleInstrumentedTest.kt:5</ID>
    <ID>NoWildcardImports:se.linerotech.module202.project6.ExampleUnitTest.kt:3</ID>
    <ID>NoWildcardImports:se.linerotech.module203.guide.ExampleInstrumentedTest.kt:5</ID>
    <ID>NoWildcardImports:se.linerotech.module203.guide.ExampleUnitTest.kt:3</ID>
    <ID>NoWildcardImports:se.linerotech.module203.project1.ExampleInstrumentedTest.kt:5</ID>
    <ID>NoWildcardImports:se.linerotech.module203.project1.ExampleUnitTest.kt:3</ID>
    <ID>NoWildcardImports:se.linerotech.module203.project2.ExampleInstrumentedTest.kt:5</ID>
    <ID>NoWildcardImports:se.linerotech.module203.project2.ExampleUnitTest.kt:3</ID>
    <ID>NoWildcardImports:se.linerotech.module203.project3.ExampleInstrumentedTest.kt:5</ID>
    <ID>NoWildcardImports:se.linerotech.module203.project3.ExampleUnitTest.kt:3</ID>
    <ID>NoWildcardImports:se.linerotech.module203.project4.ExampleInstrumentedTest.kt:5</ID>
    <ID>NoWildcardImports:se.linerotech.module203.project4.ExampleUnitTest.kt:3</ID>
    <ID>NoWildcardImports:se.linerotech.module203.project5.ExampleInstrumentedTest.kt:5</ID>
    <ID>NoWildcardImports:se.linerotech.module203.project5.ExampleUnitTest.kt:3</ID>
    <ID>NoWildcardImports:se.linerotech.module203.project6.ExampleInstrumentedTest.kt:5</ID>
    <ID>NoWildcardImports:se.linerotech.module203.project6.ExampleUnitTest.kt:3</ID>
    <ID>NoWildcardImports:se.linerotech.module204.guide.ExampleInstrumentedTest.kt:5</ID>
    <ID>NoWildcardImports:se.linerotech.module204.guide.ExampleUnitTest.kt:3</ID>
    <ID>NoWildcardImports:se.linerotech.module204.project1.ExampleInstrumentedTest.kt:5</ID>
    <ID>NoWildcardImports:se.linerotech.module204.project1.ExampleUnitTest.kt:3</ID>
    <ID>NoWildcardImports:se.linerotech.module204.project2.ExampleInstrumentedTest.kt:5</ID>
    <ID>NoWildcardImports:se.linerotech.module204.project2.ExampleUnitTest.kt:3</ID>
    <ID>NoWildcardImports:se.linerotech.module204.project3.ExampleInstrumentedTest.kt:5</ID>
    <ID>NoWildcardImports:se.linerotech.module204.project3.ExampleUnitTest.kt:3</ID>
    <ID>NoWildcardImports:se.linerotech.module204.project4.ExampleInstrumentedTest.kt:5</ID>
    <ID>NoWildcardImports:se.linerotech.module204.project4.ExampleUnitTest.kt:3</ID>
    <ID>NoWildcardImports:se.linerotech.module204.project5.ExampleInstrumentedTest.kt:5</ID>
    <ID>NoWildcardImports:se.linerotech.module204.project5.ExampleUnitTest.kt:3</ID>
    <ID>NoWildcardImports:se.linerotech.module204.project6.ExampleInstrumentedTest.kt:5</ID>
    <ID>NoWildcardImports:se.linerotech.module204.project6.ExampleUnitTest.kt:3</ID>
    <ID>NoWildcardImports:se.linerotech.module205.guide.ExampleInstrumentedTest.kt:5</ID>
    <ID>NoWildcardImports:se.linerotech.module205.guide.ExampleUnitTest.kt:3</ID>
    <ID>NoWildcardImports:se.linerotech.module205.project1.ExampleInstrumentedTest.kt:5</ID>
    <ID>NoWildcardImports:se.linerotech.module205.project1.ExampleUnitTest.kt:3</ID>
    <ID>NoWildcardImports:se.linerotech.module205.project2.ExampleInstrumentedTest.kt:5</ID>
    <ID>NoWildcardImports:se.linerotech.module205.project2.ExampleUnitTest.kt:3</ID>
    <ID>NoWildcardImports:se.linerotech.module205.project3.ExampleInstrumentedTest.kt:5</ID>
    <ID>NoWildcardImports:se.linerotech.module205.project3.ExampleUnitTest.kt:3</ID>
    <ID>NoWildcardImports:se.linerotech.module205.project4.ExampleInstrumentedTest.kt:5</ID>
    <ID>NoWildcardImports:se.linerotech.module205.project4.ExampleUnitTest.kt:3</ID>
    <ID>NoWildcardImports:se.linerotech.module205.project6.ExampleInstrumentedTest.kt:5</ID>
    <ID>NoWildcardImports:se.linerotech.module205.project6.ExampleUnitTest.kt:3</ID>
    <ID>NoWildcardImports:se.linerotech.module206.project1.ExampleInstrumentedTest.kt:5</ID>
    <ID>NoWildcardImports:se.linerotech.module206.project1.ExampleUnitTest.kt:3</ID>
    <ID>TooManyFunctions:CreateAccountActivity.kt$CreateAccountActivity : AppCompatActivity</ID>
    <ID>TooManyFunctions:LoginActivity.kt$LoginActivity : AppCompatActivity</ID>
    <ID>TooManyFunctions:RegisterActivity.kt$RegisterActivity : AppCompatActivity</ID>
    <ID>TooManyFunctions:TipsyActivity.kt$TipsyActivity : AppCompatActivity</ID>
    <ID>WildcardImport:ExampleInstrumentedTest.kt$import org.junit.Assert.*</ID>
    <ID>WildcardImport:ExampleUnitTest.kt$import org.junit.Assert.*</ID>
  </CurrentIssues>
</SmellBaseline>
